<?xml version="1.0" encoding="utf-8"?>
	<annotation>
		<folder>driving_annotation_dataset</folder>
		<filename>00181.jpg</filename>
		<size>
			<width>5472</width>
			<height>3648</height>
			<depth>3</depth>
		</size>
		<object>
			<name>二化螟</name>
			<pose>Unspecified</pose>
			<truncated>0</truncated>
			<difficult>0</difficult>
			<bndbox>
				<xmin>2167</xmin>
				<ymin>60</ymin>
				<xmax>2588</xmax>
				<ymax>498</ymax>
			</bndbox>
		</object>
		<object>
			<name>大黑鳃金龟</name>
			<pose>Unspecified</pose>
			<truncated>0</truncated>
			<difficult>0</difficult>
			<bndbox>
				<xmin>3605</xmin>
				<ymin>3387</ymin>
				<xmax>4165</xmax>
				<ymax>3656</ymax>
			</bndbox>
		</object>
		<object>
			<name>二化螟</name>
			<pose>Unspecified</pose>
			<truncated>0</truncated>
			<difficult>0</difficult>
			<bndbox>
				<xmin>2167</xmin>
				<ymin>60</ymin>
				<xmax>2588</xmax>
				<ymax>498</ymax>
			</bndbox>
		</object>
		<object>
			<name>大黑鳃金龟</name>
			<pose>Unspecified</pose>
			<truncated>0</truncated>
			<difficult>0</difficult>
			<bndbox>
				<xmin>3605</xmin>
				<ymin>3387</ymin>
				<xmax>4165</xmax>
				<ymax>3656</ymax>
			</bndbox>
		</object>
	</annotation>
